_imcpy.cpython-312-x86_64-linux-gnu.so
_imcpy.pyi
imcpy/__init__.py
imcpy/common.py
imcpy/decorators.py
imcpy/exception.py
imcpy/lsf.py
imcpy/node.py
imcpy/actors/__init__.py
imcpy/actors/base.py
imcpy/actors/dynamic.py
imcpy/actors/playback.py
imcpy/algorithms/__init__.py
imcpy/algorithms/__init__.pyi
imcpy/coordinates/__init__.py
imcpy/coordinates/__init__.pyi
imcpy/network/__init__.py
imcpy/network/tcp.py
imcpy/network/udp.py
imcpy/network/utils.py
imcpy-1.1.2.dist-info/METADATA
imcpy-1.1.2.dist-info/WHEEL
imcpy-1.1.2.dist-info/top_level.txt
imcpy-1.1.2.dist-info/RECORD
imcpy-1.1.2.dist-info/licenses/LICENSE
