Metadata-Version: 2.4
Name: imcpy
Version: 1.1.2
Summary: Python bindings for DUNE-IMC
Home-page: https://github.com/oysstu/imcpy
Author: Oystein Sture
Author-email: oysstu@gmail.com
License: MIT
Project-URL: Bug Tracker, https://github.com/oysstu/imcpy/issues
Classifier: Programming Language :: Python :: 3
Classifier: License :: OSI Approved :: MIT License
Classifier: Intended Audience :: Developers
Classifier: Intended Audience :: Other Audience
Classifier: Intended Audience :: Science/Research
Classifier: Topic :: Scientific/Engineering
Requires-Python: >=3.6
License-File: LICENSE
Requires-Dist: ifaddr
Provides-Extra: lsfexporter
Requires-Dist: pandas; extra == "lsfexporter"
Dynamic: author
Dynamic: author-email
Dynamic: classifier
Dynamic: description
Dynamic: description-content-type
Dynamic: home-page
Dynamic: license
Dynamic: license-file
Dynamic: project-url
Dynamic: provides-extra
Dynamic: requires-dist
Dynamic: requires-python
Dynamic: summary
